cysignals/__init__.py
cysignals/pselect.cpython-311-i386-linux-gnu.so
cysignals/signals.pxd
cysignals/cysignals_config.h
cysignals/pysignals.pxd
cysignals/struct_signals.h
cysignals/tests.cpython-311-i386-linux-gnu.so
cysignals/pysignals.cpython-311-i386-linux-gnu.so
cysignals/cysignals-CSI-helper.py
cysignals/memory.pxd
cysignals/alarm.cpython-311-i386-linux-gnu.so
cysignals/signals.cpython-311-i386-linux-gnu.so
cysignals/macros.h
cysignals-1.12.4.dist-info/METADATA
cysignals-1.12.4.dist-info/RECORD
cysignals-1.12.4.dist-info/LICENSE
cysignals-1.12.4.dist-info/WHEEL
cysignals-1.12.4.data/scripts/cysignals-CSI
