Metadata-Version: 2.1
Name: cysignals
Version: 1.12.4
Summary: Interrupt and signal handling for Cython
Author-Email: The Sage Developers <sage-support@googlegroups.com>
License:                    GNU LESSER GENERAL PUBLIC LICENSE
Classifier: Development Status :: 6 - Mature
Classifier: Intended Audience :: Developers
Classifier: License :: OSI Approved :: GNU Lesser General Public License v3 or later (LGPLv3+)
Classifier: Operating System :: POSIX
Classifier: Operating System :: MacOS :: MacOS X
Classifier: Programming Language :: C
Classifier: Programming Language :: Cython
Classifier: Programming Language :: Python
Classifier: Programming Language :: Python :: 3 :: Only
Classifier: Programming Language :: Python :: 3.9
Classifier: Programming Language :: Python :: 3.10
Classifier: Programming Language :: Python :: 3.11
Classifier: Programming Language :: Python :: 3.12
Classifier: Programming Language :: Python :: Implementation :: CPython
Classifier: Topic :: System
Classifier: Topic :: Software Development :: Debuggers
Project-URL: Homepage, https://github.com/sagemath/cysignals
Requires-Python: >=3.9
